ldapom_model/__init__.py
test_server/__init__.py
ldapom_model-0.2.0.dist-info/METADATA
ldapom_model-0.2.0.dist-info/WHEEL
ldapom_model-0.2.0.dist-info/top_level.txt
ldapom_model-0.2.0.dist-info/RECORD
