Metadata-Version: 2.1
Name: ldapom-model
Version: 0.2.0
Summary: Base class to manage models with ldapom.
Home-page: http://github.com/sysnove/ldapom-model
Author: Guillaume Subiron
Author-email: maethor+pip@subiron.org
License: WTFPL
Classifier: Programming Language :: Python
Classifier: Operating System :: OS Independent
Classifier: Intended Audience :: Developers
Classifier: Programming Language :: Python :: 3.3
Requires-Dist: ldapom >=0.12.1
